pycircstat-0.0.2.dist-info/DESCRIPTION.rst
pycircstat-0.0.2.dist-info/RECORD
pycircstat-0.0.2.dist-info/top_level.txt
pycircstat-0.0.2.dist-info/metadata.json
pycircstat-0.0.2.dist-info/METADATA
pycircstat-0.0.2.dist-info/WHEEL
pycircstat/descriptive.py
pycircstat/regression.py
pycircstat/event_series.py
pycircstat/iterators.py
pycircstat/distributions.py
pycircstat/data.py
pycircstat/__init__.py
pycircstat/decorators.py
pycircstat/tests.py
pycircstat/clustering.py
pycircstat/utils.py
tests/test_decorators.py
tests/test_tests.py
tests/test_distributions.py
tests/test_event_series.py
tests/test_utils.py
tests/test_regression.py
tests/test_clustering.py
tests/__init__.py
tests/test_descriptive.py
