Metadata-Version: 2.0
Name: pycircstat
Version: 0.0.2
Summary: Toolbox for circular statistics with Python
Home-page: UNKNOWN
Author: Fabian Sinz, Philipp Berens, Matthias Kuemmerer, Tom Wallis
Author-email: philipp.berens@uni-tuebingen.de
License: UNKNOWN
Keywords: statistics
Platform: UNKNOWN
Classifier: Development Status :: 3 - Alpha
Classifier: Topic :: Utilities
